{"assets/audio/endgame.mp3":["assets/audio/endgame.mp3"],"assets/audio/lose.mp3":["assets/audio/lose.mp3"],"assets/audio/onepiece.mp3":["assets/audio/onepiece.mp3"],"assets/audio/space_music.mp3":["assets/audio/space_music.mp3"],"assets/audio/win.mp3":["assets/audio/win.mp3"],"assets/fonts/Fredoka/Fredoka-Bold.ttf":["assets/fonts/Fredoka/Fredoka-Bold.ttf"],"assets/fonts/Fredoka/Fredoka-Regular.ttf":["assets/fonts/Fredoka/Fredoka-Regular.ttf"],"assets/fonts/Nunito/Nunito-Bold.ttf":["assets/fonts/Nunito/Nunito-Bold.ttf"],"assets/fonts/Nunito/Nunito-Regular.ttf":["assets/fonts/Nunito/Nunito-Regular.ttf"],"assets/fonts/PrincessSofia/PrincessSofia-Regular.ttf":["assets/fonts/PrincessSofia/PrincessSofia-Regular.ttf"],"assets/fonts/Sunnyspells/Sunnyspells-Regular.otf":["assets/fonts/Sunnyspells/Sunnyspells-Regular.otf"],"assets/images/animals/buffalo.png":["assets/images/animals/buffalo.png"],"assets/images/animals/camel.png":["assets/images/animals/camel.png"],"assets/images/animals/cat.png":["assets/images/animals/cat.png"],"assets/images/animals/cheetah.png":["assets/images/animals/cheetah.png"],"assets/images/animals/chicken.png":["assets/images/animals/chicken.png"],"assets/images/animals/chimpanzee.png":["assets/images/animals/chimpanzee.png"],"assets/images/animals/crab.png":["assets/images/animals/crab.png"],"assets/images/animals/crocodile.png":["assets/images/animals/crocodile.png"],"assets/images/animals/deer.png":["assets/images/animals/deer.png"],"assets/images/animals/dog.png":["assets/images/animals/dog.png"],"assets/images/animals/dolphin.png":["assets/images/animals/dolphin.png"],"assets/images/animals/duck.png":["assets/images/animals/duck.png"],"assets/images/animals/eagle.png":["assets/images/animals/eagle.png"],"assets/images/animals/elephant.png":["assets/images/animals/elephant.png"],"assets/images/animals/fish.png":["assets/images/animals/fish.png"],"assets/images/animals/fox.png":["assets/images/animals/fox.png"],"assets/images/animals/giraffe.png":["assets/images/animals/giraffe.png"],"assets/images/animals/goat.png":["assets/images/animals/goat.png"],"assets/images/animals/gorilla.png":["assets/images/animals/gorilla.png"],"assets/images/animals/hippopotamus.png":["assets/images/animals/hippopotamus.png"],"assets/images/animals/horse.png":["assets/images/animals/horse.png"],"assets/images/animals/kangaroo.png":["assets/images/animals/kangaroo.png"],"assets/images/animals/leopard.png":["assets/images/animals/leopard.png"],"assets/images/animals/lion.png":["assets/images/animals/lion.png"],"assets/images/animals/monkey.png":["assets/images/animals/monkey.png"],"assets/images/animals/mouse.png":["assets/images/animals/mouse.png"],"assets/images/animals/mule.png":["assets/images/animals/mule.png"],"assets/images/animals/octopus.png":["assets/images/animals/octopus.png"],"assets/images/animals/ostrich.png":["assets/images/animals/ostrich.png"],"assets/images/animals/owl.png":["assets/images/animals/owl.png"],"assets/images/animals/ox.png":["assets/images/animals/ox.png"],"assets/images/animals/panther.png":["assets/images/animals/panther.png"],"assets/images/animals/parrot.png":["assets/images/animals/parrot.png"],"assets/images/animals/penguin.png":["assets/images/animals/penguin.png"],"assets/images/animals/rhinoceros.png":["assets/images/animals/rhinoceros.png"],"assets/images/animals/shark.png":["assets/images/animals/shark.png"],"assets/images/animals/sheep.png":["assets/images/animals/sheep.png"],"assets/images/animals/squirrel.png":["assets/images/animals/squirrel.png"],"assets/images/animals/tiger.png":["assets/images/animals/tiger.png"],"assets/images/animals/turtle.png":["assets/images/animals/turtle.png"],"assets/images/animals/whale.png":["assets/images/animals/whale.png"],"assets/images/animals/wolf.png":["assets/images/animals/wolf.png"],"assets/images/animals/zebra.png":["assets/images/animals/zebra.png"],"assets/images/banner/.gitkeep":["assets/images/banner/.gitkeep"],"assets/images/banner/banner1.png":["assets/images/banner/banner1.png"],"assets/images/banner/banner2.png":["assets/images/banner/banner2.png"],"assets/images/banner/banner3.png":["assets/images/banner/banner3.png"],"assets/images/banner/banner4.png":["assets/images/banner/banner4.png"],"assets/images/colors/Aqua.png":["assets/images/colors/Aqua.png"],"assets/images/colors/Beige.png":["assets/images/colors/Beige.png"],"assets/images/colors/Black.png":["assets/images/colors/Black.png"],"assets/images/colors/Blue.png":["assets/images/colors/Blue.png"],"assets/images/colors/Bronze.png":["assets/images/colors/Bronze.png"],"assets/images/colors/Brown.png":["assets/images/colors/Brown.png"],"assets/images/colors/Burgundy.png":["assets/images/colors/Burgundy.png"],"assets/images/colors/Coral.png":["assets/images/colors/Coral.png"],"assets/images/colors/Cream.png":["assets/images/colors/Cream.png"],"assets/images/colors/Cyan.png":["assets/images/colors/Cyan.png"],"assets/images/colors/Golden.png":["assets/images/colors/Golden.png"],"assets/images/colors/Gray.png":["assets/images/colors/Gray.png"],"assets/images/colors/Green.png":["assets/images/colors/Green.png"],"assets/images/colors/Lavender.png":["assets/images/colors/Lavender.png"],"assets/images/colors/Lime.png":["assets/images/colors/Lime.png"],"assets/images/colors/Magenta.png":["assets/images/colors/Magenta.png"],"assets/images/colors/Maroon.png":["assets/images/colors/Maroon.png"],"assets/images/colors/Mustard.png":["assets/images/colors/Mustard.png"],"assets/images/colors/NavyBlue.png":["assets/images/colors/NavyBlue.png"],"assets/images/colors/Olive.png":["assets/images/colors/Olive.png"],"assets/images/colors/Orange.png":["assets/images/colors/Orange.png"],"assets/images/colors/Peach.png":["assets/images/colors/Peach.png"],"assets/images/colors/Pink.png":["assets/images/colors/Pink.png"],"assets/images/colors/Purple.png":["assets/images/colors/Purple.png"],"assets/images/colors/Red.png":["assets/images/colors/Red.png"],"assets/images/colors/Rust.png":["assets/images/colors/Rust.png"],"assets/images/colors/Silver.png":["assets/images/colors/Silver.png"],"assets/images/colors/Teal.png":["assets/images/colors/Teal.png"],"assets/images/colors/White.png":["assets/images/colors/White.png"],"assets/images/colors/Yellow.png":["assets/images/colors/Yellow.png"],"assets/images/feedings/ChubbyBoy.png":["assets/images/feedings/ChubbyBoy.png"],"assets/images/fruits/apple.png":["assets/images/fruits/apple.png"],"assets/images/fruits/apricot.png":["assets/images/fruits/apricot.png"],"assets/images/fruits/avocado.png":["assets/images/fruits/avocado.png"],"assets/images/fruits/banana.png":["assets/images/fruits/banana.png"],"assets/images/fruits/blueberry.png":["assets/images/fruits/blueberry.png"],"assets/images/fruits/cactus_fruit.png":["assets/images/fruits/cactus_fruit.png"],"assets/images/fruits/cherry.png":["assets/images/fruits/cherry.png"],"assets/images/fruits/citron.png":["assets/images/fruits/citron.png"],"assets/images/fruits/coconut.png":["assets/images/fruits/coconut.png"],"assets/images/fruits/date.png":["assets/images/fruits/date.png"],"assets/images/fruits/fig.png":["assets/images/fruits/fig.png"],"assets/images/fruits/grape.png":["assets/images/fruits/grape.png"],"assets/images/fruits/guava.png":["assets/images/fruits/guava.png"],"assets/images/fruits/lemon.png":["assets/images/fruits/lemon.png"],"assets/images/fruits/lychee.png":["assets/images/fruits/lychee.png"],"assets/images/fruits/mango.png":["assets/images/fruits/mango.png"],"assets/images/fruits/nectarine.png":["assets/images/fruits/nectarine.png"],"assets/images/fruits/orange.png":["assets/images/fruits/orange.png"],"assets/images/fruits/papaya.png":["assets/images/fruits/papaya.png"],"assets/images/fruits/passion_fruit.png":["assets/images/fruits/passion_fruit.png"],"assets/images/fruits/peach.png":["assets/images/fruits/peach.png"],"assets/images/fruits/pear.png":["assets/images/fruits/pear.png"],"assets/images/fruits/pineapple.png":["assets/images/fruits/pineapple.png"],"assets/images/fruits/plum.png":["assets/images/fruits/plum.png"],"assets/images/fruits/pomegranate.png":["assets/images/fruits/pomegranate.png"],"assets/images/fruits/soursop.png":["assets/images/fruits/soursop.png"],"assets/images/fruits/strawberry.png":["assets/images/fruits/strawberry.png"],"assets/images/fruits/tangerine.png":["assets/images/fruits/tangerine.png"],"assets/images/fruits/watermelon.png":["assets/images/fruits/watermelon.png"],"assets/images/fruits/white_sapote.png":["assets/images/fruits/white_sapote.png"],"assets/images/logos/.gitkeep":["assets/images/logos/.gitkeep"],"assets/images/logos/logo1.png":["assets/images/logos/logo1.png"],"assets/images/spaces/astronaut.png":["assets/images/spaces/astronaut.png"],"assets/images/spaces/chicken_astronaut.png":["assets/images/spaces/chicken_astronaut.png"],"assets/images/spaces/earth.png":["assets/images/spaces/earth.png"],"assets/images/spaces/jupiter.png":["assets/images/spaces/jupiter.png"],"assets/images/spaces/mars.png":["assets/images/spaces/mars.png"],"assets/images/spaces/mercury.png":["assets/images/spaces/mercury.png"],"assets/images/spaces/space_map_full.png":["assets/images/spaces/space_map_full.png"],"assets/images/spaces/space_single.png":["assets/images/spaces/space_single.png"],"assets/images/spaces/sun.png":["assets/images/spaces/sun.png"],"assets/images/spaces/venus.png":["assets/images/spaces/venus.png"],"assets/images/treasures/chick_character.png":["assets/images/treasures/chick_character.png"],"assets/images/treasures/treasure_banner.png":["assets/images/treasures/treasure_banner.png"],"assets/images/treasures/treasure_bg.png":["assets/images/treasures/treasure_bg.png"],"assets/images/treasures/treasure_chest.png":["assets/images/treasures/treasure_chest.png"],"assets/images/treasures/treasure_map.png":["assets/images/treasures/treasure_map.png"],"assets/images/treasures/treasure_pirateking1.png":["assets/images/treasures/treasure_pirateking1.png"],"assets/images/treasures/treasure_pirateking2.png":["assets/images/treasures/treasure_pirateking2.png"],"assets/images/treasures/treasure_pirateking3.png":["assets/images/treasures/treasure_pirateking3.png"],"assets/images/treasures/treasure_pirateking4.png":["assets/images/treasures/treasure_pirateking4.png"],"assets/images/treasures/treasure_pirateking5.png":["assets/images/treasures/treasure_pirateking5.png"],"assets/sounds/success_bell.mp3":["assets/sounds/success_bell.mp3"],"assets/sounds/success_bell2.mp3":["assets/sounds/success_bell2.mp3"],"assets/translations/en-US.json":["assets/translations/en-US.json"],"assets/translations/ja-JP.json":["assets/translations/ja-JP.json"],"assets/translations/vi.json":["assets/translations/vi.json"],"packages/cupertino_icons/assets/CupertinoIcons.ttf":["packages/cupertino_icons/assets/CupertinoIcons.ttf"],"packages/font_awesome_flutter/lib/fonts/fa-brands-400.ttf":["packages/font_awesome_flutter/lib/fonts/fa-brands-400.ttf"],"packages/font_awesome_flutter/lib/fonts/fa-regular-400.ttf":["packages/font_awesome_flutter/lib/fonts/fa-regular-400.ttf"],"packages/font_awesome_flutter/lib/fonts/fa-solid-900.ttf":["packages/font_awesome_flutter/lib/fonts/fa-solid-900.ttf"]}